geoenv/__init__.py
geoenv/data/__init__.py
geoenv/data/data_source_attributes/wte_attribute_table.json
geoenv/data/sssom/EcologicalCoastalUnits-envo.sssom.tsv
geoenv/data/sssom/EcologicalCoastalUnits-envo.sssom.yml
geoenv/data/sssom/EcologicalMarineUnits-envo.sssom.tsv
geoenv/data/sssom/EcologicalMarineUnits-envo.sssom.yml
geoenv/data/sssom/WorldTerrestrialEcosystems-envo.sssom.tsv
geoenv/data/sssom/WorldTerrestrialEcosystems-envo.sssom.yml
geoenv/data_sources/__init__.py
geoenv/data_sources/data_source.py
geoenv/data_sources/ecological_coastal_units.py
geoenv/data_sources/ecological_marine_units.py
geoenv/data_sources/world_terrestrial_ecosystems.py
geoenv/environment.py
geoenv/geometry.py
geoenv/resolver.py
geoenv/response.py
geoenv/utilities.py
geoenv-0.4.1.dist-info/METADATA
geoenv-0.4.1.dist-info/WHEEL
geoenv-0.4.1.dist-info/licenses/LICENSE
geoenv-0.4.1.dist-info/RECORD
