Metadata-Version: 2.4
Name: geoenv
Version: 0.4.1
Summary: Map geometries to environmental semantics
License: MIT
License-File: LICENSE
Author: Colin Smith
Author-email: colin.smith@wisc.edu
Maintainer: Colin Smith
Maintainer-email: colin.smith@wisc.edu
Requires-Python: >=3.11
Classifier: License :: OSI Approved :: MIT License
Classifier: Programming Language :: Python :: 3
Classifier: Programming Language :: Python :: 3.11
Classifier: Programming Language :: Python :: 3.12
Classifier: Programming Language :: Python :: 3.13
Classifier: Programming Language :: Python :: 3.14
Requires-Dist: aiohttp (>=3.12.15,<4.0.0)
Requires-Dist: daiquiri (>=3.3.0,<4.0.0)
Requires-Dist: geopandas (>=1.0.1,<2.0.0)
Requires-Dist: pandas (>=2.2.3,<3.0.0)
Requires-Dist: requests (>=2.32.3,<3.0.0)
